AUTHORS.rst
LICENSE
README.rst
setup.py
realalg/__init__.py
realalg/base_algebraic.py
realalg/cypari2_algebraic.py
realalg/cypari_algebraic.py
realalg/interval.py
realalg/sympy_algebraic.py
realalg.egg-info/PKG-INFO
realalg.egg-info/SOURCES.txt
realalg.egg-info/dependency_links.txt
realalg.egg-info/not-zip-safe
realalg.egg-info/requires.txt
realalg.egg-info/top_level.txt