Metadata-Version: 2.1
Name: realalg
Version: 0.3.4
Summary: For manipulating real algebraic numbers
Home-page: https://github.com/MarkCBell/realalg
Author: Mark Bell
Author-email: mcbell@illinois.edu
License: MIT License
Keywords: algebraic
Platform: UNKNOWN
Classifier: Development Status :: 3 - Alpha
Classifier: Intended Audience :: Education
Classifier: Intended Audience :: Science/Research
Classifier: License :: OSI Approved :: MIT License
Classifier: Natural Language :: English
Classifier: Operating System :: OS Independent
Classifier: Programming Language :: Python
Classifier: Topic :: Scientific/Engineering :: Mathematics
License-File: LICENSE
License-File: AUTHORS.rst
